examples/__init__.py
examples/celeba_example.py
examples/cifar10_example.py
examples/sent140_example.py
flsim/__init__.py
flsim/version.py
flsim/active_user_selectors/__init__.py
flsim/active_user_selectors/simple_user_selector.py
flsim/active_user_selectors/tests/__init__.py
flsim/active_user_selectors/tests/test_active_user_selector.py
flsim/channels/__init__.py
flsim/channels/base_channel.py
flsim/channels/communication_stats.py
flsim/channels/half_precision_channel.py
flsim/channels/message.py
flsim/channels/product_quantization_channel.py
flsim/channels/scalar_quantization_channel.py
flsim/channels/sparse_mask_channel.py
flsim/channels/pq_utils/__init__.py
flsim/channels/pq_utils/em.py
flsim/channels/pq_utils/pq.py
flsim/channels/pq_utils/tests/__init__.py
flsim/channels/pq_utils/tests/test_product_quantization.py
flsim/channels/tests/__init__.py
flsim/channels/tests/test_half_precision_channel.py
flsim/channels/tests/test_identity_channel.py
flsim/channels/tests/test_product_quantization_channel.py
flsim/channels/tests/test_scalar_quantization_channel.py
flsim/channels/tests/test_sparse_mask_channel.py
flsim/clients/__init__.py
flsim/clients/async_client.py
flsim/clients/base_client.py
flsim/clients/dp_client.py
flsim/clients/sync_mime_client.py
flsim/clients/sync_mimelite_client.py
flsim/clients/tests/__init__.py
flsim/clients/tests/test_async_client.py
flsim/clients/tests/test_client.py
flsim/common/__init__.py
flsim/common/diversity_metrics.py
flsim/common/fine_tuner.py
flsim/common/logger.py
flsim/common/pytest_helper.py
flsim/common/timeline.py
flsim/common/timeout_simulator.py
flsim/common/training_event_handler.py
flsim/common/training_simulator.py
flsim/common/tests/__init__.py
flsim/common/tests/test_diversity_metrics.py
flsim/common/tests/test_fine_tuner.py
flsim/common/tests/test_round_timeline.py
flsim/common/tests/test_timeout_simulator.py
flsim/common/tests/test_training_event_handler.py
flsim/common/tests/test_training_simulator.py
flsim-0.1.0.dist-info/LICENSE
flsim-0.1.0.dist-info/METADATA
flsim-0.1.0.dist-info/WHEEL
flsim-0.1.0.dist-info/top_level.txt
flsim-0.1.0.dist-info/RECORD
